Compiled from "tailrec-factorial.kt"
final class Tailrec_factorialKt$tailRecFactorial$1 extends kotlin.jvm.internal.Lambda implements kotlin.jvm.functions.Function2<java.lang.Integer, java.lang.Integer, java.lang.Integer> {
  public static final Tailrec_factorialKt$tailRecFactorial$1 INSTANCE;

  public java.lang.Object invoke(java.lang.Object, java.lang.Object);
    Code:
       0: aload_0
       1: aload_1
       2: checkcast     #11                 // class java/lang/Number
       5: invokevirtual #15                 // Method java/lang/Number.intValue:()I
       8: aload_2
       9: checkcast     #11                 // class java/lang/Number
      12: invokevirtual #15                 // Method java/lang/Number.intValue:()I
      15: invokevirtual #18                 // Method invoke:(II)I
      18: invokestatic  #24                 // Method java/lang/Integer.valueOf:(I)Ljava/lang/Integer;
      21: areturn

  public final int invoke(int, int);
    Code:
       0: iload_1
       1: iconst_1
       2: if_icmpge     9
       5: iload_2
       6: goto          25
       9: aload_0
      10: checkcast     #2                  // class Tailrec_factorialKt$tailRecFactorial$1
      13: pop
      14: iload_1
      15: iconst_1
      16: isub
      17: iload_2
      18: iload_1
      19: imul
      20: istore_2
      21: istore_1
      22: goto          0
      25: ireturn

  Tailrec_factorialKt$tailRecFactorial$1();
    Code:
       0: aload_0
       1: iconst_2
       2: invokespecial #34                 // Method kotlin/jvm/internal/Lambda."<init>":(I)V
       5: return

  static {};
    Code:
       0: new           #2                  // class Tailrec_factorialKt$tailRecFactorial$1
       3: dup
       4: invokespecial #56                 // Method "<init>":()V
       7: putstatic     #58                 // Field INSTANCE:LTailrec_factorialKt$tailRecFactorial$1;
      10: return
}
