Compiled from "numeric.kt"
public final class NumericKt {
  public static final int getAnInt();
    Code:
       0: getstatic     #11                 // Field anInt:I
       3: ireturn

  public static final long getALong();
    Code:
       0: getstatic     #19                 // Field aLong:J
       3: lreturn

  public static final java.lang.Double getADouble();
    Code:
       0: getstatic     #26                 // Field aDouble:Ljava/lang/Double;
       3: areturn

  public static final void setADouble(java.lang.Double);
    Code:
       0: aload_0
       1: putstatic     #26                 // Field aDouble:Ljava/lang/Double;
       4: return

  static {};
    Code:
       0: bipush        42
       2: putstatic     #11                 // Field anInt:I
       5: ldc2_w        #14                 // long 42l
       8: putstatic     #19                 // Field aLong:J
      11: return
}