Compiled from "default-value.kt"
public final class _03_fun.Default_valueKt {
  public static final java.lang.String buildString2(java.lang.String, java.lang.String, boolean);
    Code:
       0: aload_0
       1: ldc           #9                  // String prefix
       3: invokestatic  #15                 // Method kotlin/jvm/internal/Intrinsics.checkParameterIsNotNull:(Ljava/lang/Object;Ljava/lang/String;)V
       6: aload_1
       7: ldc           #17                 // String who
       9: invokestatic  #15                 // Method kotlin/jvm/internal/Intrinsics.checkParameterIsNotNull:(Ljava/lang/Object;Ljava/lang/String;)V
      12: new           #19                 // class java/lang/StringBuilder
      15: dup
      16: invokespecial #23                 // Method java/lang/StringBuilder."<init>":()V
      19: ldc           #25                 // String
      21: invokevirtual #29                 // Method java/lang/StringBuilder.append:(Ljava/lang/String;)Ljava/lang/StringBuilder;
      24: aload_0
      25: invokevirtual #29                 // Method java/lang/StringBuilder.append:(Ljava/lang/String;)Ljava/lang/StringBuilder;
      28: bipush        32
      30: invokevirtual #32                 // Method java/lang/StringBuilder.append:(C)Ljava/lang/StringBuilder;
      33: aload_1
      34: invokevirtual #29                 // Method java/lang/StringBuilder.append:(Ljava/lang/String;)Ljava/lang/StringBuilder;
      37: invokevirtual #36                 // Method java/lang/StringBuilder.toString:()Ljava/lang/String;
      40: astore_3
      41: iload_2
      42: ifeq          66
      45: aload_3
      46: new           #19                 // class java/lang/StringBuilder
      49: dup
      50: invokespecial #23                 // Method java/lang/StringBuilder."<init>":()V
      53: swap
      54: invokevirtual #29                 // Method java/lang/StringBuilder.append:(Ljava/lang/String;)Ljava/lang/StringBuilder;
      57: bipush        33
      59: invokevirtual #32                 // Method java/lang/StringBuilder.append:(C)Ljava/lang/StringBuilder;
      62: invokevirtual #36                 // Method java/lang/StringBuilder.toString:()Ljava/lang/String;
      65: astore_3
      66: aload_3
      67: areturn

  public static java.lang.String buildString2$default(java.lang.String, java.lang.String, boolean, int, java.lang.Object);
    Code:
       0: iload_3
       1: iconst_1
       2: iand
       3: ifeq          9
       6: ldc           #46                 // String Hello
       8: astore_0
       9: iload_3
      10: iconst_4
      11: iand
      12: ifeq          17
      15: iconst_1
      16: istore_2
      17: aload_0
      18: aload_1
      19: iload_2
      20: invokestatic  #48                 // Method buildString2:(Ljava/lang/String;Ljava/lang/String;Z)Ljava/lang/String;
      23: areturn

  public static final java.lang.String greetings2();
    Code:
       0: aconst_null
       1: ldc           #51                 // String RivieraDev
       3: iconst_0
       4: iconst_5
       5: aconst_null
       6: invokestatic  #53                 // Method buildString2$default:(Ljava/lang/String;Ljava/lang/String;ZILjava/lang/Object;)Ljava/lang/String;
       9: areturn
}